camtty/__init__.py
camtty/app.py
camtty/ascii_converter.py
camtty/cam_to_ascii.py
camtty/camera_handler.py
camtty/terminal_display.py
camtty-0.1.1.dist-info/licenses/LICENSE
camtty-0.1.1.dist-info/METADATA
camtty-0.1.1.dist-info/WHEEL
camtty-0.1.1.dist-info/entry_points.txt
camtty-0.1.1.dist-info/top_level.txt
camtty-0.1.1.dist-info/RECORD
