Metadata-Version: 2.4
Name: camtty
Version: 0.1.1
Summary: A CLI tool to display webcam feed as ASCII art in the terminal
Author-email: Abderrahman Gaga <agaga@student.hive.fi>
Keywords: webcam,ascii-art,terminal,cli,video,camera,ascii,tty
Classifier: Development Status :: 4 - Beta
Classifier: Intended Audience :: Developers
Classifier: Intended Audience :: End Users/Desktop
Classifier: Programming Language :: Python :: 3
Classifier: Programming Language :: Python :: 3.8
Classifier: Programming Language :: Python :: 3.9
Classifier: Programming Language :: Python :: 3.10
Classifier: Programming Language :: Python :: 3.11
Classifier: Programming Language :: Python :: 3.12
Classifier: Programming Language :: Python :: 3.13
Classifier: Operating System :: OS Independent
Requires-Python: >=3.7
License-File: LICENSE
Requires-Dist: opencv-python
Requires-Dist: numpy
Requires-Dist: blessed
Dynamic: license-file
